<views>
    <view entity="sec$Group" name="group-browse">
        <property name="name"/>
        <property name="parent"/>
    </view>

    <view entity="sec$User" name="group-browse">
        <property name="name"/>
    </view>

    <view entity="sec$Subject" name="group-browse">
        <property name="defaultSubject"/>
        <property name="user" view="group-browse"/>
        <property name="profile" view="group-browse"/>
    </view>

    <view entity="sec$Profile" name="group-browse">
        <property name="name"/>
    </view>
</views>