<!--
  ~ Copyright (c) 2008-2013 Haulmont. All rights reserved.
  ~ Use is subject to license terms, see http://www.cuba-platform.com/license for details.
  -->

<window xmlns="http://schemas.haulmont.com/cuba/window.xsd"
        class="com.haulmont.cuba.gui.app.core.about.AboutWindow"
        caption="msg://caption">

    <dialogMode width="theme://cuba.gui.AboutWindow.width"
                height="theme://cuba.gui.AboutWindow.height"
                resizable="false"/>

    <layout>
        <tabSheet width="100%" height="100%">
            <tab id="infoTab" caption="msg://info" margin="true" spacing="true">
                <frame id="license" screen="licenseFrame" width="100%" height="100%"/>
            </tab>
            <tab id="creditsTab" caption="msg://credits" margin="true">
                <frame id="credits" screen="creditsFrame" width="100%" height="100%"/>
            </tab>
        </tabSheet>
    </layout>
</window>